COPYING
COPYING.mit
MANIFEST.in
README.md
requirements.txt
setup.py
forbiddenfruit/__init__.py
forbiddenfruit.egg-info/PKG-INFO
forbiddenfruit.egg-info/SOURCES.txt
forbiddenfruit.egg-info/dependency_links.txt
forbiddenfruit.egg-info/top_level.txt
tests/__init__.py
tests/__pycache__/__init__.cpython-37.pyc
tests/unit/__init__.py
tests/unit/ffruit.c
tests/unit/ffruit.cpython-37m-x86_64-linux-gnu.so
tests/unit/test_forbidden_fruit.py
tests/unit/__pycache__/__init__.cpython-37.pyc
tests/unit/__pycache__/test_forbidden_fruit.cpython-37.pyc