Metadata-Version: 2.1
Name: forbiddenfruit
Version: 0.1.4
Summary: Patch python built-in objects
Home-page: https://github.com/clarete/forbiddenfruit
Author: Lincoln de Sousa
Author-email: lincoln@clarete.li
License: UNKNOWN
Platform: UNKNOWN
Classifier: License :: OSI Approved :: GNU General Public License v3 or later (GPLv3+)
Classifier: License :: OSI Approved :: MIT License
